{ "columns":4,
 "image":"..\/entities\/entity-catchef.png",
 "imageheight":240,
 "imagewidth":192,
 "margin":0,
 "name":"entity-catchef",
 "spacing":0,
 "tilecount":20,
 "tiledversion":"1.9.2",
 "tileheight":48,
 "tiles":[
        {
         "animation":[
                {
                 "duration":150,
                 "tileid":0
                }, 
                {
                 "duration":150,
                 "tileid":0
                }],
         "class":"catchef",
         "id":0
        }, 
        {
         "animation":[
                {
                 "duration":150,
                 "tileid":1
                }, 
                {
                 "duration":150,
                 "tileid":1
                }],
         "class":"catchef",
         "id":1
        }, 
        {
         "animation":[
                {
                 "duration":150,
                 "tileid":2
                }, 
                {
                 "duration":150,
                 "tileid":2
                }],
         "class":"catchef",
         "id":2
        }, 
        {
         "animation":[
                {
                 "duration":150,
                 "tileid":3
                }, 
                {
                 "duration":150,
                 "tileid":3
                }],
         "class":"catchef",
         "id":3
        }, 
        {
         "animation":[
                {
                 "duration":150,
                 "tileid":4
                }, 
                {
                 "duration":150,
                 "tileid":8
                }, 
                {
                 "duration":150,
                 "tileid":12
                }, 
                {
                 "duration":150,
                 "tileid":16
                }],
         "class":"catchef",
         "id":4
        }, 
        {
         "animation":[
                {
                 "duration":150,
                 "tileid":5
                }, 
                {
                 "duration":150,
                 "tileid":9
                }, 
                {
                 "duration":150,
                 "tileid":13
                }, 
                {
                 "duration":150,
                 "tileid":17
                }],
         "class":"catchef",
         "id":5
        }, 
        {
         "animation":[
                {
                 "duration":150,
                 "tileid":6
                }, 
                {
                 "duration":150,
                 "tileid":10
                }, 
                {
                 "duration":150,
                 "tileid":14
                }, 
                {
                 "duration":150,
                 "tileid":18
                }],
         "class":"catchef",
         "id":6
        }, 
        {
         "animation":[
                {
                 "duration":150,
                 "tileid":7
                }, 
                {
                 "duration":150,
                 "tileid":11
                }, 
                {
                 "duration":150,
                 "tileid":15
                }, 
                {
                 "duration":150,
                 "tileid":19
                }],
         "class":"catchef",
         "id":7
        }, 
        {
         "class":"catchef",
         "id":8
        }, 
        {
         "class":"catchef",
         "id":9
        }, 
        {
         "class":"catchef",
         "id":10
        }, 
        {
         "class":"catchef",
         "id":11
        }, 
        {
         "class":"catchef",
         "id":12
        }, 
        {
         "class":"catchef",
         "id":13
        }, 
        {
         "class":"catchef",
         "id":14
        }, 
        {
         "class":"catchef",
         "id":15
        }, 
        {
         "class":"catchef",
         "id":16
        }, 
        {
         "class":"catchef",
         "id":17
        }, 
        {
         "class":"catchef",
         "id":18
        }, 
        {
         "class":"catchef",
         "id":19
        }],
 "tilewidth":48,
 "type":"tileset",
 "version":"1.9"
}