{ "compressionlevel":-1,
 "height":12,
 "infinite":false,
 "layers":[
        {
         "data":[0, 0, 0, 0, 0, 0, 0, 0, 0, 0, 0, 0,
            0, 255, 256, 260, 256, 256, 256, 256, 260, 256, 2147483903, 0,
            0, 271, 272, 276, 272, 261, 2147483909, 272, 276, 272, 2147483919, 0,
            0, 287, 288, 288, 288, 288, 288, 288, 288, 288, 2147483935, 0,
            0, 287, 288, 288, 288, 288, 288, 288, 288, 288, 2147483935, 0,
            0, 287, 288, 288, 288, 288, 288, 288, 288, 288, 2147483925, 0,
            0, 287, 288, 288, 288, 288, 288, 288, 288, 288, 2147483941, 0,
            0, 287, 288, 288, 288, 288, 288, 288, 288, 288, 2147483935, 0,
            0, 287, 288, 288, 288, 288, 288, 288, 288, 288, 2147483935, 0,
            0, 303, 288, 288, 288, 288, 288, 288, 288, 288, 2147483951, 0,
            0, 319, 320, 320, 320, 320, 320, 321, 321, 320, 2147483967, 0,
            0, 0, 0, 0, 0, 0, 0, 0, 0, 0, 0, 0],
         "height":12,
         "id":6,
         "name":"Floor",
         "opacity":1,
         "type":"tilelayer",
         "visible":true,
         "width":12,
         "x":0,
         "y":0
        }, 
        {
         "data":[0, 0, 0, 0, 0, 0, 0, 0, 0, 0, 0, 0,
            0, 0, 0, 0, 0, 0, 0, 0, 0, 0, 0, 0,
            0, 0, 0, 0, 0, 355, 356, 0, 0, 0, 0, 0,
            0, 0, 403, 0, 0, 371, 372, 0, 0, 403, 0, 0,
            0, 0, 367, 2147484016, 2147484015, 0, 0, 367, 2147484016, 2147484015, 0, 0,
            0, 0, 402, 264, 268, 269, 264, 269, 402, 355, 0, 0,
            0, 0, 0, 267, 268, 350, 0, 311, 0, 371, 0, 0,
            0, 0, 402, 347, 268, 265, 264, 282, 265, 0, 0, 0,
            0, 0, 0, 0, 0, 0, 0, 0, 0, 403, 0, 0,
            0, 0, 367, 2147484016, 2147484015, 402, 0, 367, 2147484016, 2147484015, 0, 0,
            0, 0, 0, 0, 0, 0, 0, 0, 0, 0, 0, 0,
            0, 0, 0, 0, 0, 0, 0, 0, 0, 0, 0, 0],
         "height":12,
         "id":7,
         "name":"Floor Doodads",
         "opacity":1,
         "type":"tilelayer",
         "visible":true,
         "width":12,
         "x":0,
         "y":0
        }, 
        {
         "data":[0, 0, 0, 0, 0, 0, 0, 0, 0, 0, 0, 0,
            0, 0, 0, 0, 0, 0, 0, 0, 0, 0, 0, 0,
            0, 0, 0, 0, 0, 0, 0, 0, 0, 0, 0, 0,
            0, 0, 335, 2147483984, 2147483983, 0, 0, 335, 2147483984, 2147483983, 0, 0,
            0, 0, 386, 0, 0, 0, 0, 0, 387, 0, 0, 0,
            0, 0, 0, 0, 0, 0, 0, 0, 0, 0, 356, 0,
            0, 0, 386, 0, 0, 0, 0, 0, 0, 0, 372, 0,
            0, 0, 0, 0, 0, 0, 0, 0, 0, 0, 0, 0,
            0, 0, 335, 2147483984, 2147483983, 2147484034, 0, 335, 2147483984, 2147483983, 0, 0,
            0, 0, 0, 0, 0, 0, 0, 0, 0, 0, 0, 0,
            0, 0, 0, 0, 0, 0, 0, 0, 0, 0, 0, 0,
            0, 0, 0, 0, 0, 0, 0, 0, 0, 0, 0, 0],
         "height":12,
         "id":8,
         "name":"Floating Layer",
         "opacity":1,
         "type":"tilelayer",
         "visible":true,
         "width":12,
         "x":0,
         "y":0
        }, 
        {
         "draworder":"topdown",
         "id":3,
         "name":"Entities",
         "objects":[
                {
                 "class":"",
                 "height":0,
                 "id":6,
                 "name":"warp-spot",
                 "point":true,
                 "rotation":0,
                 "visible":true,
                 "width":0,
                 "x":196,
                 "y":216
                }, 
                {
                 "class":"",
                 "gid":253,
                 "height":32,
                 "id":19,
                 "name":"door",
                 "properties":[
                        {
                         "name":"on_interact",
                         "type":"string",
                         "value":"ch2-attempt-door-check"
                        }],
                 "rotation":0,
                 "visible":true,
                 "width":32,
                 "x":176,
                 "y":95
                }, 
                {
                 "class":"",
                 "gid":165,
                 "height":32,
                 "id":31,
                 "name":"Bub",
                 "properties":[
                        {
                         "name":"is_player",
                         "type":"bool",
                         "value":true
                        }],
                 "rotation":0,
                 "visible":true,
                 "width":32,
                 "x":284,
                 "y":220
                }, 
                {
                 "class":"",
                 "gid":777,
                 "height":32,
                 "id":32,
                 "name":"abacus",
                 "properties":[
                        {
                         "name":"on_interact",
                         "type":"string",
                         "value":"ch2-touch-abacus"
                        }],
                 "rotation":0,
                 "visible":true,
                 "width":32,
                 "x":231,
                 "y":283
                }, 
                {
                 "class":"",
                 "gid":801,
                 "height":48,
                 "id":34,
                 "name":"Goose",
                 "properties":[
                        {
                         "name":"on_interact",
                         "type":"string",
                         "value":"show_dialog-goose-generic"
                        }],
                 "rotation":0,
                 "visible":true,
                 "width":48,
                 "x":279,
                 "y":172
                }, 
                {
                 "class":"",
                 "gid":2147484527,
                 "height":32,
                 "id":36,
                 "name":"Jean-Paul",
                 "properties":[
                        {
                         "name":"on_interact",
                         "type":"string",
                         "value":"interact-ch2-jeanpaul"
                        }],
                 "rotation":0,
                 "visible":true,
                 "width":32,
                 "x":66,
                 "y":274
                }, 
                {
                 "class":"",
                 "gid":901,
                 "height":32,
                 "id":37,
                 "name":"Frankie",
                 "properties":[
                        {
                         "name":"on_interact",
                         "type":"string",
                         "value":"interact-ch2-frankie"
                        }],
                 "rotation":0,
                 "visible":true,
                 "width":32,
                 "x":127,
                 "y":273
                }],
         "opacity":1,
         "type":"objectgroup",
         "visible":true,
         "x":0,
         "y":0
        }, 
        {
         "draworder":"topdown",
         "id":5,
         "name":"Vectors",
         "objects":[
                {
                 "class":"",
                 "height":0,
                 "id":15,
                 "name":"",
                 "point":true,
                 "rotation":0,
                 "visible":true,
                 "width":0,
                 "x":-154,
                 "y":462
                }, 
                {
                 "class":"",
                 "height":0,
                 "id":33,
                 "name":"hiding-spot",
                 "point":true,
                 "rotation":0,
                 "visible":true,
                 "width":0,
                 "x":-41.5,
                 "y":-26.5
                }],
         "opacity":1,
         "type":"objectgroup",
         "visible":true,
         "x":0,
         "y":0
        }],
 "nextlayerid":9,
 "nextobjectid":38,
 "orientation":"orthogonal",
 "renderorder":"right-down",
 "tiledversion":"1.9.2",
 "tileheight":32,
 "tilesets":[
        {
         "firstgid":1,
         "source":"..\/tilesets\/tileset-monstrosity.json"
        }, 
        {
         "firstgid":161,
         "source":"..\/entities\/entity-mage.json"
        }, 
        {
         "firstgid":209,
         "source":"..\/entities\/entity-exa.json"
        }, 
        {
         "firstgid":211,
         "source":"..\/entities\/entity-save_floppy.json"
        }, 
        {
         "firstgid":235,
         "source":"..\/entities\/entity-bert.json"
        }, 
        {
         "firstgid":253,
         "source":"..\/entities\/entity-null.json"
        }, 
        {
         "firstgid":255,
         "source":"tileset-castle-interior.json"
        }, 
        {
         "firstgid":511,
         "source":"..\/tilesets\/tileset-town.json"
        }, 
        {
         "firstgid":767,
         "source":"..\/entities\/entity-goldfish.json"
        }, 
        {
         "firstgid":777,
         "source":"..\/entities\/entity-abacus.json"
        }, 
        {
         "firstgid":801,
         "source":"..\/entities\/entity-goose-bow.json"
        }, 
        {
         "firstgid":843,
         "source":"..\/entities\/entity-welder.json"
        },
    
        {
         "firstgid":867,
         "source":"..\/entities\/entity-cockatiel.json"
        }, 
        {
         "firstgid":888,
         "source":"..\/entities\/entity-npc01.json"
        }],
 "tilewidth":32,
 "type":"map",
 "version":"1.9",
 "width":12
}