{ "columns":4,
 "image":"tileset-testbig.png",
 "imageheight":256,
 "imagewidth":256,
 "margin":0,
 "name":"tileset-testbig",
 "spacing":0,
 "tilecount":16,
 "tiledversion":"1.4.3",
 "tileheight":64,
 "tiles":[
        {
         "id":0,
         "objectgroup":
            {
             "draworder":"index",
             "id":2,
             "name":"",
             "objects":[
                    {
                     "height":63.8721590909091,
                     "id":1,
                     "name":"",
                     "rotation":0,
                     "type":"",
                     "visible":true,
                     "width":47.8693181818182,
                     "x":0.0681818181818182,
                     "y":0.0653409090909091
                    }],
             "opacity":1,
             "type":"objectgroup",
             "visible":true,
             "x":0,
             "y":0
            }
        }, 
        {
         "id":1,
         "objectgroup":
            {
             "draworder":"index",
             "id":2,
             "name":"",
             "objects":[
                    {
                     "height":0,
                     "id":1,
                     "name":"",
                     "polygon":[
                            {
                             "x":0,
                             "y":0
                            }, 
                            {
                             "x":-0.125,
                             "y":63.5
                            }, 
                            {
                             "x":63.5,
                             "y":63.5
                            }],
                     "rotation":0,
                     "type":"",
                     "visible":true,
                     "width":0,
                     "x":0.375,
                     "y":0.25
                    }],
             "opacity":1,
             "type":"objectgroup",
             "visible":true,
             "x":0,
             "y":0
            }
        }, 
        {
         "id":2,
         "objectgroup":
            {
             "draworder":"index",
             "id":2,
             "name":"",
             "objects":[
                    {
                     "height":0,
                     "id":1,
                     "name":"",
                     "polygon":[
                            {
                             "x":-0.125,
                             "y":-0.25
                            }, 
                            {
                             "x":-0.25,
                             "y":63.5
                            }, 
                            {
                             "x":31.5,
                             "y":63.5
                            }],
                     "rotation":0,
                     "type":"",
                     "visible":true,
                     "width":0,
                     "x":0.375,
                     "y":0.375
                    }],
             "opacity":1,
             "type":"objectgroup",
             "visible":true,
             "x":0,
             "y":0
            }
        }, 
        {
         "id":3,
         "objectgroup":
            {
             "draworder":"index",
             "id":2,
             "name":"",
             "objects":[
                    {
                     "height":0,
                     "id":1,
                     "name":"",
                     "polygon":[
                            {
                             "x":0,
                             "y":0
                            }, 
                            {
                             "x":0,
                             "y":63.75
                            }, 
                            {
                             "x":15.625,
                             "y":63.5
                            }],
                     "rotation":0,
                     "type":"",
                     "visible":true,
                     "width":0,
                     "x":0.25,
                     "y":0.25
                    }],
             "opacity":1,
             "type":"objectgroup",
             "visible":true,
             "x":0,
             "y":0
            }
        }, 
        {
         "id":4,
         "objectgroup":
            {
             "draworder":"index",
             "id":2,
             "name":"",
             "objects":[
                    {
                     "height":0,
                     "id":1,
                     "name":"",
                     "polygon":[
                            {
                             "x":0,
                             "y":0
                            }, 
                            {
                             "x":0,
                             "y":63.5
                            }, 
                            {
                             "x":31.5,
                             "y":63.625
                            }, 
                            {
                             "x":31.5,
                             "y":31.5
                            }, 
                            {
                             "x":63.625,
                             "y":31.5
                            }, 
                            {
                             "x":63.625,
                             "y":0.125
                            }],
                     "rotation":0,
                     "type":"",
                     "visible":true,
                     "width":0,
                     "x":0.25,
                     "y":0.25
                    }],
             "opacity":1,
             "type":"objectgroup",
             "visible":true,
             "x":0,
             "y":0
            }
        }, 
        {
         "id":5,
         "objectgroup":
            {
             "draworder":"index",
             "id":2,
             "name":"",
             "objects":[
                    {
                     "height":0,
                     "id":1,
                     "name":"",
                     "polygon":[
                            {
                             "x":0,
                             "y":0
                            }, 
                            {
                             "x":-16.25,
                             "y":16.25
                            }, 
                            {
                             "x":-16.25,
                             "y":47.125
                            }, 
                            {
                             "x":0,
                             "y":63.5
                            }, 
                            {
                             "x":31,
                             "y":63.5
                            }, 
                            {
                             "x":47.125,
                             "y":47
                            }, 
                            {
                             "x":47.25,
                             "y":16.25
                            }, 
                            {
                             "x":30.625,
                             "y":-0.125
                            }],
                     "rotation":0,
                     "type":"",
                     "visible":true,
                     "width":0,
                     "x":16.625,
                     "y":0.375
                    }],
             "opacity":1,
             "type":"objectgroup",
             "visible":true,
             "x":0,
             "y":0
            }
        }, 
        {
         "id":6,
         "objectgroup":
            {
             "draworder":"index",
             "id":2,
             "name":"",
             "objects":[
                    {
                     "height":0,
                     "id":1,
                     "name":"",
                     "polygon":[
                            {
                             "x":0,
                             "y":0
                            }, 
                            {
                             "x":0,
                             "y":63.75
                            }, 
                            {
                             "x":63.75,
                             "y":63.75
                            }, 
                            {
                             "x":31.25,
                             "y":0
                            }],
                     "rotation":0,
                     "type":"",
                     "visible":true,
                     "width":0,
                     "x":0.25,
                     "y":0.125
                    }],
             "opacity":1,
             "type":"objectgroup",
             "visible":true,
             "x":0,
             "y":0
            }
        }, 
        {
         "id":7,
         "objectgroup":
            {
             "draworder":"index",
             "id":2,
             "name":"",
             "objects":[
                    {
                     "height":0,
                     "id":1,
                     "name":"",
                     "polygon":[
                            {
                             "x":0,
                             "y":-0.25
                            }, 
                            {
                             "x":0,
                             "y":63.5
                            }, 
                            {
                             "x":31.75,
                             "y":63.5
                            }, 
                            {
                             "x":15.5,
                             "y":-0.125
                            }],
                     "rotation":0,
                     "type":"",
                     "visible":true,
                     "width":0,
                     "x":0.25,
                     "y":0.375
                    }],
             "opacity":1,
             "type":"objectgroup",
             "visible":true,
             "x":0,
             "y":0
            }
        }, 
        {
         "id":9,
         "objectgroup":
            {
             "draworder":"index",
             "id":2,
             "name":"",
             "objects":[
                    {
                     "height":0,
                     "id":1,
                     "name":"",
                     "polygon":[
                            {
                             "x":0,
                             "y":0
                            }, 
                            {
                             "x":0,
                             "y":63.625
                            }, 
                            {
                             "x":48,
                             "y":47.875
                            }, 
                            {
                             "x":16.5,
                             "y":31.5
                            }, 
                            {
                             "x":47.75,
                             "y":15.875
                            }],
                     "rotation":0,
                     "type":"",
                     "visible":true,
                     "width":0,
                     "x":0.25,
                     "y":0.25
                    }],
             "opacity":1,
             "type":"objectgroup",
             "visible":true,
             "x":0,
             "y":0
            }
        }, 
        {
         "id":10,
         "objectgroup":
            {
             "draworder":"index",
             "id":2,
             "name":"",
             "objects":[
                    {
                     "height":0,
                     "id":1,
                     "name":"",
                     "polygon":[
                            {
                             "x":0.125,
                             "y":0
                            }, 
                            {
                             "x":15.625,
                             "y":0
                            }, 
                            {
                             "x":15.75,
                             "y":48
                            }, 
                            {
                             "x":63.625,
                             "y":48
                            }, 
                            {
                             "x":63.625,
                             "y":63.375
                            }, 
                            {
                             "x":0.125,
                             "y":63.625
                            }],
                     "rotation":0,
                     "type":"",
                     "visible":true,
                     "width":0,
                     "x":0.125,
                     "y":0.25
                    }],
             "opacity":1,
             "type":"objectgroup",
             "visible":true,
             "x":0,
             "y":0
            }
        }, 
        {
         "id":11,
         "objectgroup":
            {
             "draworder":"index",
             "id":2,
             "name":"",
             "objects":[
                    {
                     "height":0,
                     "id":1,
                     "name":"",
                     "polygon":[
                            {
                             "x":-0.125,
                             "y":0.125
                            }, 
                            {
                             "x":31.5,
                             "y":0.125
                            }, 
                            {
                             "x":47.5,
                             "y":63.625
                            }, 
                            {
                             "x":0,
                             "y":63.625
                            }],
                     "rotation":0,
                     "type":"",
                     "visible":true,
                     "width":0,
                     "x":0.25,
                     "y":0.125
                    }],
             "opacity":1,
             "type":"objectgroup",
             "visible":true,
             "x":0,
             "y":0
            }
        }, 
        {
         "id":12,
         "objectgroup":
            {
             "draworder":"index",
             "id":2,
             "name":"",
             "objects":[
                    {
                     "height":0,
                     "id":1,
                     "name":"",
                     "polygon":[
                            {
                             "x":0,
                             "y":0
                            }, 
                            {
                             "x":0,
                             "y":63.75
                            }, 
                            {
                             "x":63.625,
                             "y":63.75
                            }, 
                            {
                             "x":63.5,
                             "y":0.125
                            }, 
                            {
                             "x":62.625,
                             "y":10.125
                            }, 
                            {
                             "x":59.125,
                             "y":19.25
                            }, 
                            {
                             "x":53.125,
                             "y":24.875
                            }, 
                            {
                             "x":43,
                             "y":30.75
                            }, 
                            {
                             "x":35.625,
                             "y":32
                            }, 
                            {
                             "x":25.75,
                             "y":32.125
                            }, 
                            {
                             "x":16.75,
                             "y":29.5
                            }, 
                            {
                             "x":10.375,
                             "y":25.125
                            }, 
                            {
                             "x":4.875,
                             "y":19.375
                            }, 
                            {
                             "x":2,
                             "y":12.125
                            }],
                     "rotation":0,
                     "type":"",
                     "visible":true,
                     "width":0,
                     "x":0.25,
                     "y":0.125
                    }],
             "opacity":1,
             "type":"objectgroup",
             "visible":true,
             "x":0,
             "y":0
            }
        }, 
        {
         "id":13,
         "objectgroup":
            {
             "draworder":"index",
             "id":2,
             "name":"",
             "objects":[
                    {
                     "height":0,
                     "id":1,
                     "name":"",
                     "polygon":[
                            {
                             "x":0,
                             "y":0
                            }, 
                            {
                             "x":-0.125,
                             "y":63.375
                            }, 
                            {
                             "x":63.625,
                             "y":63.5
                            }, 
                            {
                             "x":63.625,
                             "y":57.875
                            }, 
                            {
                             "x":62.625,
                             "y":55.375
                            }, 
                            {
                             "x":60.25,
                             "y":52.25
                            }, 
                            {
                             "x":55.875,
                             "y":51.375
                            }, 
                            {
                             "x":46.25,
                             "y":50.625
                            }, 
                            {
                             "x":39.125,
                             "y":49.625
                            }, 
                            {
                             "x":33.375,
                             "y":47.75
                            }, 
                            {
                             "x":30.25,
                             "y":44.625
                            }, 
                            {
                             "x":27.875,
                             "y":40.125
                            }, 
                            {
                             "x":27.625,
                             "y":21.125
                            }, 
                            {
                             "x":25.75,
                             "y":18.125
                            }, 
                            {
                             "x":20.875,
                             "y":14.875
                            }, 
                            {
                             "x":15.5,
                             "y":13.75
                            }, 
                            {
                             "x":10.125,
                             "y":10.25
                            }, 
                            {
                             "x":6.5,
                             "y":3.75
                            }, 
                            {
                             "x":3.25,
                             "y":1.5
                            }],
                     "rotation":0,
                     "type":"",
                     "visible":true,
                     "width":0,
                     "x":0.25,
                     "y":0.25
                    }],
             "opacity":1,
             "type":"objectgroup",
             "visible":true,
             "x":0,
             "y":0
            }
        }, 
        {
         "id":14,
         "objectgroup":
            {
             "draworder":"index",
             "id":2,
             "name":"",
             "objects":[
                    {
                     "height":0,
                     "id":1,
                     "name":"",
                     "polygon":[
                            {
                             "x":0,
                             "y":0
                            }, 
                            {
                             "x":0,
                             "y":63.375
                            }, 
                            {
                             "x":63.625,
                             "y":63.5
                            }, 
                            {
                             "x":48.375,
                             "y":31.75
                            }, 
                            {
                             "x":31.875,
                             "y":31.875
                            }, 
                            {
                             "x":31.625,
                             "y":15.75
                            }],
                     "rotation":0,
                     "type":"",
                     "visible":true,
                     "width":0,
                     "x":0.25,
                     "y":0.375
                    }],
             "opacity":1,
             "type":"objectgroup",
             "visible":true,
             "x":0,
             "y":0
            }
        }, 
        {
         "id":15,
         "objectgroup":
            {
             "draworder":"index",
             "id":2,
             "name":"",
             "objects":[
                    {
                     "height":0,
                     "id":1,
                     "name":"",
                     "polygon":[
                            {
                             "x":0,
                             "y":0
                            }, 
                            {
                             "x":0,
                             "y":63.3757338551859
                            }, 
                            {
                             "x":63.75,
                             "y":63.5004892367906
                            }, 
                            {
                             "x":48.25,
                             "y":-0.124510763209393
                            }],
                     "rotation":0,
                     "type":"",
                     "visible":true,
                     "width":0,
                     "x":0.25,
                     "y":0.374510763209393
                    }],
             "opacity":1,
             "type":"objectgroup",
             "visible":true,
             "x":0,
             "y":0
            }
        }],
 "tilewidth":64,
 "type":"tileset",
 "version":1.4
}