{ "columns":100,
 "image":"..\/entities\/entity-keyboard.png",
 "imageheight":32,
 "imagewidth":3200,
 "margin":0,
 "name":"entity-keyboard",
 "spacing":0,
 "tilecount":100,
 "tiledversion":"1.9.2",
 "tileheight":32,
 "tiles":[
        {
         "animation":[
                {
                 "duration":30,
                 "tileid":0
                }, 
                {
                 "duration":30,
                 "tileid":1
                }, 
                {
                 "duration":30,
                 "tileid":2
                }, 
                {
                 "duration":30,
                 "tileid":3
                }, 
                {
                 "duration":30,
                 "tileid":4
                }, 
                {
                 "duration":30,
                 "tileid":5
                }, 
                {
                 "duration":30,
                 "tileid":6
                }, 
                {
                 "duration":30,
                 "tileid":7
                }, 
                {
                 "duration":30,
                 "tileid":8
                }, 
                {
                 "duration":30,
                 "tileid":9
                }, 
                {
                 "duration":30,
                 "tileid":10
                }, 
                {
                 "duration":30,
                 "tileid":11
                }, 
                {
                 "duration":30,
                 "tileid":12
                }, 
                {
                 "duration":30,
                 "tileid":13
                }, 
                {
                 "duration":30,
                 "tileid":14
                }, 
                {
                 "duration":30,
                 "tileid":15
                }, 
                {
                 "duration":30,
                 "tileid":16
                }, 
                {
                 "duration":30,
                 "tileid":17
                }, 
                {
                 "duration":30,
                 "tileid":18
                }, 
                {
                 "duration":30,
                 "tileid":19
                }, 
                {
                 "duration":30,
                 "tileid":20
                }, 
                {
                 "duration":30,
                 "tileid":21
                }, 
                {
                 "duration":30,
                 "tileid":22
                }, 
                {
                 "duration":30,
                 "tileid":23
                }, 
                {
                 "duration":30,
                 "tileid":24
                }, 
                {
                 "duration":30,
                 "tileid":25
                }, 
                {
                 "duration":30,
                 "tileid":26
                }, 
                {
                 "duration":30,
                 "tileid":27
                }, 
                {
                 "duration":30,
                 "tileid":28
                }, 
                {
                 "duration":30,
                 "tileid":29
                }, 
                {
                 "duration":30,
                 "tileid":30
                }, 
                {
                 "duration":30,
                 "tileid":31
                }, 
                {
                 "duration":30,
                 "tileid":32
                }, 
                {
                 "duration":30,
                 "tileid":33
                }, 
                {
                 "duration":30,
                 "tileid":34
                }, 
                {
                 "duration":30,
                 "tileid":35
                }, 
                {
                 "duration":30,
                 "tileid":36
                }, 
                {
                 "duration":30,
                 "tileid":37
                }, 
                {
                 "duration":30,
                 "tileid":38
                }, 
                {
                 "duration":30,
                 "tileid":39
                }, 
                {
                 "duration":30,
                 "tileid":40
                }, 
                {
                 "duration":30,
                 "tileid":41
                }, 
                {
                 "duration":30,
                 "tileid":42
                }, 
                {
                 "duration":30,
                 "tileid":43
                }, 
                {
                 "duration":30,
                 "tileid":44
                }, 
                {
                 "duration":30,
                 "tileid":44
                }, 
                {
                 "duration":30,
                 "tileid":45
                }, 
                {
                 "duration":30,
                 "tileid":46
                }, 
                {
                 "duration":30,
                 "tileid":47
                }, 
                {
                 "duration":30,
                 "tileid":48
                }, 
                {
                 "duration":30,
                 "tileid":49
                }, 
                {
                 "duration":30,
                 "tileid":50
                }, 
                {
                 "duration":30,
                 "tileid":51
                }, 
                {
                 "duration":30,
                 "tileid":52
                }, 
                {
                 "duration":30,
                 "tileid":53
                }, 
                {
                 "duration":30,
                 "tileid":54
                }, 
                {
                 "duration":30,
                 "tileid":55
                }, 
                {
                 "duration":30,
                 "tileid":56
                }, 
                {
                 "duration":30,
                 "tileid":57
                }, 
                {
                 "duration":30,
                 "tileid":58
                }, 
                {
                 "duration":30,
                 "tileid":59
                }, 
                {
                 "duration":30,
                 "tileid":60
                }, 
                {
                 "duration":30,
                 "tileid":61
                }, 
                {
                 "duration":30,
                 "tileid":62
                }, 
                {
                 "duration":30,
                 "tileid":63
                }, 
                {
                 "duration":30,
                 "tileid":64
                }, 
                {
                 "duration":30,
                 "tileid":65
                }, 
                {
                 "duration":30,
                 "tileid":66
                }, 
                {
                 "duration":30,
                 "tileid":67
                }, 
                {
                 "duration":30,
                 "tileid":68
                }, 
                {
                 "duration":30,
                 "tileid":69
                }, 
                {
                 "duration":30,
                 "tileid":70
                }, 
                {
                 "duration":30,
                 "tileid":71
                }, 
                {
                 "duration":30,
                 "tileid":72
                }, 
                {
                 "duration":30,
                 "tileid":73
                }, 
                {
                 "duration":30,
                 "tileid":74
                }, 
                {
                 "duration":30,
                 "tileid":75
                }, 
                {
                 "duration":30,
                 "tileid":76
                }, 
                {
                 "duration":30,
                 "tileid":77
                }, 
                {
                 "duration":30,
                 "tileid":78
                }, 
                {
                 "duration":30,
                 "tileid":79
                }, 
                {
                 "duration":30,
                 "tileid":80
                }, 
                {
                 "duration":30,
                 "tileid":81
                }, 
                {
                 "duration":30,
                 "tileid":82
                }, 
                {
                 "duration":30,
                 "tileid":83
                }, 
                {
                 "duration":30,
                 "tileid":84
                }, 
                {
                 "duration":30,
                 "tileid":85
                }, 
                {
                 "duration":30,
                 "tileid":86
                }, 
                {
                 "duration":30,
                 "tileid":87
                }, 
                {
                 "duration":30,
                 "tileid":88
                }, 
                {
                 "duration":30,
                 "tileid":89
                }, 
                {
                 "duration":30,
                 "tileid":90
                }, 
                {
                 "duration":30,
                 "tileid":91
                }, 
                {
                 "duration":30,
                 "tileid":92
                }, 
                {
                 "duration":30,
                 "tileid":93
                }, 
                {
                 "duration":30,
                 "tileid":94
                }, 
                {
                 "duration":30,
                 "tileid":95
                }, 
                {
                 "duration":30,
                 "tileid":96
                }, 
                {
                 "duration":30,
                 "tileid":97
                }, 
                {
                 "duration":30,
                 "tileid":98
                }, 
                {
                 "duration":30,
                 "tileid":99
                }, 
                {
                 "duration":30,
                 "tileid":99
                }],
         "id":0
        }],
 "tilewidth":32,
 "type":"tileset",
 "version":"1.9"
}